LICENSE
MANIFEST.in
setup.py
thegiant/25compat.h
thegiant/__init__.py
thegiant/__init__.pyc
thegiant/common.c
thegiant/common.h
thegiant/filewrapper.c
thegiant/filewrapper.h
thegiant/helpers.py
thegiant/helpers.pyc
thegiant/request.c
thegiant/request.h
thegiant/server.c
thegiant/server.h
thegiant/server.so
thegiant/thegiantmodule.c
thegiant/thegiantmodule.h
thegiant/wsgi.c
thegiant/wsgi.h
thegiant.egg-info/PKG-INFO
thegiant.egg-info/SOURCES.txt
thegiant.egg-info/dependency_links.txt
thegiant.egg-info/requires.txt
thegiant.egg-info/top_level.txt