Metadata-Version: 1.1
Name: thegiant
Version: 1.2.1
Summary: A wsgi server that speaks Redis written in C.
Home-page: https://github.com/ybrs/the-giant
Author: Aybars Badur
Author-email: aybars.badur@gmail.com
License: 2-clause BSD
Platform: UNKNOWN
Classifier: Development Status :: 4 - Beta
Classifier: License :: OSI Approved :: BSD License
Classifier: Programming Language :: C
Classifier: Programming Language :: Python
Classifier: Topic :: Internet :: WWW/HTTP :: WSGI :: Server
